[{"timestamp":"2024-04-15T00:00:00.000","min_open":0.175,"max_open":0.1976,"mode_open":0.185,"sum_open":18.1005,"mean_open":0.1866030928,"std_open":0.0067642974,"min_high":0.1762,"max_high":0.1983,"mode_high":0.1809,"sum_high":18.2017,"mean_high":0.1876463918,"std_high":0.0067861081,"min_low":0.1721,"max_low":0.1957,"mode_low":0.1841,"sum_low":17.9923,"mean_low":0.1854876289,"std_low":0.0067870627,"min_close":0.1749,"max_close":0.1978,"mode_close":0.1848,"sum_close":18.0975,"mean_close":0.1865721649,"std_close":0.0067622226,"min_volume":11619.3,"max_volume":595415.7,"mode_volume":11619.3,"sum_volume":13306192.3000000026,"mean_volume":137177.2402061856,"std_volume":108452.8988675928,"min_close_time":1713140099999,"max_close_time":1713226499999,"mode_close_time":1713140099999,"sum_close_time":166178780099903,"mean_close_time":1713183299999.0,"std_close_time":25330909.9718111195,"min_quote_asset_volume":2074.12757,"max_quote_asset_volume":103588.44236,"mode_quote_asset_volume":2074.12757,"sum_quote_asset_volume":2480642.8379900004,"mean_quote_asset_volume":25573.6375050515,"std_quote_asset_volume":20020.725212374,"min_number_of_trades":31,"max_number_of_trades":622,"mode_number_of_trades":128,"sum_number_of_trades":18586,"mean_number_of_trades":191.6082474227,"std_number_of_trades":121.2157646428,"min_taker_buy_base_asset_volume":5625.0,"max_taker_buy_base_asset_volume":238512.4,"mode_taker_buy_base_asset_volume":5625.0,"sum_taker_buy_base_asset_volume":6774795.3999999994,"mean_taker_buy_base_asset_volume":69843.2515463918,"std_taker_buy_base_asset_volume":52473.635578917,"min_taker_buy_quote_asset_volume":1005.37553,"max_taker_buy_quote_asset_volume":46763.29147,"mode_taker_buy_quote_asset_volume":1005.37553,"sum_taker_buy_quote_asset_volume":1264472.24389,"mean_taker_buy_quote_asset_volume":13035.7963287629,"std_taker_buy_quote_asset_volume":9738.4540068778,"min_ignore":0,"max_ignore":0,"mode_ignore":0,"sum_ignore":0,"mean_ignore":0.0,"std_ignore":0.0},{"timestamp":"2024-04-16T00:00:00.000","min_open":0.1727,"max_open":0.1836,"mode_open":0.1779,"sum_open":17.3186,"mean_open":0.178542268,"std_open":0.0024950299,"min_high":0.1741,"max_high":0.1839,"mode_high":0.178,"sum_high":17.4209,"mean_high":0.1795969072,"std_high":0.0022809653,"min_low":0.1713,"max_low":0.1822,"mode_low":0.1775,"sum_low":17.2201,"mean_low":0.1775268041,"std_low":0.0026696019,"min_close":0.1728,"max_close":0.1836,"mode_close":0.1784,"sum_close":17.3211,"mean_close":0.1785680412,"std_close":0.0025201912,"min_volume":25114.5,"max_volume":449759.5,"mode_volume":25114.5,"sum_volume":12203826.4000000004,"mean_volume":125812.6432989691,"std_volume":86126.1678610235,"min_close_time":1713226499999,"max_close_time":1713312899999,"mode_close_time":1713226499999,"sum_close_time":166187160899903,"mean_close_time":1713269699999.0,"std_close_time":25330909.9718111195,"min_quote_asset_volume":4545.79394,"max_quote_asset_volume":79205.85927,"mode_quote_asset_volume":4545.79394,"sum_quote_asset_volume":2174681.7720699999,"mean_quote_asset_volume":22419.3997120619,"std_quote_asset_volume":15264.017515332,"min_number_of_trades":40,"max_number_of_trades":701,"mode_number_of_trades":99,"sum_number_of_trades":19075,"mean_number_of_trades":196.6494845361,"std_number_of_trades":122.9038446338,"min_taker_buy_base_asset_volume":5997.5,"max_taker_buy_base_asset_volume":279796.5,"mode_taker_buy_base_asset_volume":5997.5,"sum_taker_buy_base_asset_volume":6218082.0,"mean_taker_buy_base_asset_volume":64103.9381443299,"std_taker_buy_base_asset_volume":50878.8422485415,"min_taker_buy_quote_asset_volume":1086.66783,"max_taker_buy_quote_asset_volume":49697.73559,"mode_taker_buy_quote_asset_volume":1086.66783,"sum_taker_buy_quote_asset_volume":1107899.1406700001,"mean_taker_buy_quote_asset_volume":11421.6406254639,"std_taker_buy_quote_asset_volume":9030.2308812719,"min_ignore":0,"max_ignore":0,"mode_ignore":0,"sum_ignore":0,"mean_ignore":0.0,"std_ignore":0.0},{"timestamp":"2024-04-17T00:00:00.000","min_open":0.169,"max_open":0.1826,"mode_open":0.1771,"sum_open":17.1718,"mean_open":0.177028866,"std_open":0.0033926685,"min_high":0.17,"max_high":0.1832,"mode_high":0.1801,"sum_high":17.2521,"mean_high":0.177856701,"std_high":0.0031884854,"min_low":0.1677,"max_low":0.1819,"mode_low":0.1782,"sum_low":17.0845,"mean_low":0.176128866,"std_low":0.0034995523,"min_close":0.1692,"max_close":0.1827,"mode_close":0.1769,"sum_close":17.1662,"mean_close":0.176971134,"std_close":0.0033895968,"min_volume":16569.5,"max_volume":757144.4,"mode_volume":16569.5,"sum_volume":18470130.6000000015,"mean_volume":190413.7175257732,"std_volume":170338.4008282209,"min_close_time":1713312899999,"max_close_time":1713399299999,"mode_close_time":1713312899999,"sum_close_time":166195541699903,"mean_close_time":1713356099999.0,"std_close_time":25330909.9718111195,"min_quote_asset_volume":2956.28741,"max_quote_asset_volume":128652.16523,"mode_quote_asset_volume":2956.28741,"sum_quote_asset_volume":3233247.93462,"mean_quote_asset_volume":33332.4529342268,"std_quote_asset_volume":29155.3683053591,"min_number_of_trades":46,"max_number_of_trades":7298,"mode_number_of_trades":61,"sum_number_of_trades":37896,"mean_number_of_trades":390.6804123711,"std_number_of_trades":798.2518731891,"min_taker_buy_base_asset_volume":7127.9,"max_taker_buy_base_asset_volume":485973.3,"mode_taker_buy_base_asset_volume":7127.9,"sum_taker_buy_base_asset_volume":9341253.0,"mean_taker_buy_base_asset_volume":96301.5773195876,"std_taker_buy_base_asset_volume":90460.7633053051,"min_taker_buy_quote_asset_volume":1271.62915,"max_taker_buy_quote_asset_volume":82657.48055,"mode_taker_buy_quote_asset_volume":1271.62915,"sum_taker_buy_quote_asset_volume":1635711.7641399999,"mean_taker_buy_quote_asset_volume":16863.007877732,"std_taker_buy_quote_asset_volume":15500.045832775,"min_ignore":0,"max_ignore":0,"mode_ignore":0,"sum_ignore":0,"mean_ignore":0.0,"std_ignore":0.0},{"timestamp":"2024-04-18T00:00:00.000","min_open":0.1701,"max_open":0.1829,"mode_open":0.1798,"sum_open":17.1853,"mean_open":0.1771680412,"std_open":0.0033312143,"min_high":0.1711,"max_high":0.1845,"mode_high":0.1765,"sum_high":17.2652,"mean_high":0.1779917526,"std_high":0.0032149932,"min_low":0.1695,"max_low":0.1824,"mode_low":0.1733,"sum_low":17.112,"mean_low":0.1764123711,"std_low":0.0033797269,"min_close":0.1702,"max_close":0.183,"mode_close":0.1817,"sum_close":17.194,"mean_close":0.177257732,"std_close":0.0033156773,"min_volume":10133.5,"max_volume":813308.4,"mode_volume":10133.5,"sum_volume":7637977.5,"mean_volume":78742.0360824742,"std_volume":86481.6548839011,"min_close_time":1713399299999,"max_close_time":1713485699999,"mode_close_time":1713399299999,"sum_close_time":166203922499903,"mean_close_time":1713442499999.0,"std_close_time":25330909.9718111195,"min_quote_asset_volume":1837.61516,"max_quote_asset_volume":147909.3503,"mode_quote_asset_volume":1837.61516,"sum_quote_asset_volume":1353881.58155,"mean_quote_asset_volume":13957.5420778351,"std_quote_asset_volume":15648.7316780074,"min_number_of_trades":39,"max_number_of_trades":891,"mode_number_of_trades":148,"sum_number_of_trades":15724,"mean_number_of_trades":162.1030927835,"std_number_of_trades":104.6352279485,"min_taker_buy_base_asset_volume":3586.6,"max_taker_buy_base_asset_volume":424884.0,"mode_taker_buy_base_asset_volume":3586.6,"sum_taker_buy_base_asset_volume":3888425.8000000003,"mean_taker_buy_base_asset_volume":40086.8639175258,"std_taker_buy_base_asset_volume":45922.5500743942,"min_taker_buy_quote_asset_volume":650.02786,"max_taker_buy_quote_asset_volume":77339.88632,"mode_taker_buy_quote_asset_volume":650.02786,"sum_taker_buy_quote_asset_volume":689527.22168,"mean_taker_buy_quote_asset_volume":7108.5280585567,"std_taker_buy_quote_asset_volume":8313.948163552,"min_ignore":0,"max_ignore":0,"mode_ignore":0,"sum_ignore":0,"mean_ignore":0.0,"std_ignore":0.0},{"timestamp":"2024-04-19T00:00:00.000","min_open":0.1664,"max_open":0.1876,"mode_open":0.1853,"sum_open":17.7285,"mean_open":0.1827680412,"std_open":0.0047792857,"min_high":0.1687,"max_high":0.1884,"mode_high":0.1862,"sum_high":17.8212,"mean_high":0.1837237113,"std_high":0.0045115309,"min_low":0.1659,"max_low":0.1866,"mode_low":0.185,"sum_low":17.6491,"mean_low":0.1819494845,"std_low":0.0050630426,"min_close":0.1665,"max_close":0.1878,"mode_close":0.185,"sum_close":17.7332,"mean_close":0.1828164948,"std_close":0.0047861275,"min_volume":14037.1,"max_volume":517721.7,"mode_volume":14037.1,"sum_volume":9990840.8000000007,"mean_volume":102998.3587628866,"std_volume":96830.8009233264,"min_close_time":1713485699999,"max_close_time":1713572099999,"mode_close_time":1713485699999,"sum_close_time":166212303299903,"mean_close_time":1713528899999.0,"std_close_time":25330909.9718111195,"min_quote_asset_volume":2610.54345,"max_quote_asset_volume":94185.21565,"mode_quote_asset_volume":2610.54345,"sum_quote_asset_volume":1810158.11402,"mean_quote_asset_volume":18661.4238558763,"std_quote_asset_volume":17388.7590328147,"min_number_of_trades":37,"max_number_of_trades":1171,"mode_number_of_trades":74,"sum_number_of_trades":20742,"mean_number_of_trades":213.8350515464,"std_number_of_trades":207.998231183,"min_taker_buy_base_asset_volume":7272.3,"max_taker_buy_base_asset_volume":252723.0,"mode_taker_buy_base_asset_volume":7272.3,"sum_taker_buy_base_asset_volume":5134163.8000000007,"mean_taker_buy_base_asset_volume":52929.5237113402,"std_taker_buy_base_asset_volume":50654.5642885996,"min_taker_buy_quote_asset_volume":1349.6153,"max_taker_buy_quote_asset_volume":46749.76836,"mode_taker_buy_quote_asset_volume":1349.6153,"sum_taker_buy_quote_asset_volume":931270.82583,"mean_taker_buy_quote_asset_volume":9600.7301631959,"std_taker_buy_quote_asset_volume":9129.9548787467,"min_ignore":0,"max_ignore":0,"mode_ignore":0,"sum_ignore":0,"mean_ignore":0.0,"std_ignore":0.0},{"timestamp":"2024-04-20T00:00:00.000","min_open":0.1823,"max_open":0.1966,"mode_open":0.1864,"sum_open":18.3281,"mean_open":0.1889494845,"std_open":0.0043245453,"min_high":0.1832,"max_high":0.197,"mode_high":0.1867,"sum_high":18.3892,"mean_high":0.1895793814,"std_high":0.0043224689,"min_low":0.1815,"max_low":0.1958,"mode_low":0.1945,"sum_low":18.2769,"mean_low":0.1884216495,"std_low":0.0043069766,"min_close":0.1823,"max_close":0.1966,"mode_close":0.1865,"sum_close":18.3395,"mean_close":0.1890670103,"std_close":0.0043557606,"min_volume":15250.0,"max_volume":286735.8,"mode_volume":15250.0,"sum_volume":9055927.0999999996,"mean_volume":93360.0731958763,"std_volume":62058.1343238061,"min_close_time":1713572099999,"max_close_time":1713658499999,"mode_close_time":1713572099999,"sum_close_time":166220684099903,"mean_close_time":1713615299999.0,"std_close_time":25330909.9718111195,"min_quote_asset_volume":2837.49978,"max_quote_asset_volume":55955.70737,"mode_quote_asset_volume":2837.49978,"sum_quote_asset_volume":1717364.27092,"mean_quote_asset_volume":17704.7862981443,"std_quote_asset_volume":11951.8381812346,"min_number_of_trades":49,"max_number_of_trades":478,"mode_number_of_trades":112,"sum_number_of_trades":14435,"mean_number_of_trades":148.8144329897,"std_number_of_trades":75.3829570008,"min_taker_buy_base_asset_volume":6477.5,"max_taker_buy_base_asset_volume":198333.5,"mode_taker_buy_base_asset_volume":6477.5,"sum_taker_buy_base_asset_volume":4657168.2999999998,"mean_taker_buy_base_asset_volume":48012.0443298969,"std_taker_buy_base_asset_volume":35712.6126066011,"min_taker_buy_quote_asset_volume":1264.24218,"max_taker_buy_quote_asset_volume":38710.14693,"mode_taker_buy_quote_asset_volume":1264.24218,"sum_taker_buy_quote_asset_volume":883526.6080600001,"mean_taker_buy_quote_asset_volume":9108.5217325773,"std_taker_buy_quote_asset_volume":6880.3003902548,"min_ignore":0,"max_ignore":0,"mode_ignore":0,"sum_ignore":0,"mean_ignore":0.0,"std_ignore":0.0},{"timestamp":"2024-04-21T00:00:00.000","min_open":0.1897,"max_open":0.1969,"mode_open":0.1935,"sum_open":18.772,"mean_open":0.1935257732,"std_open":0.0015683908,"min_high":0.1908,"max_high":0.1972,"mode_high":0.194,"sum_high":18.8254,"mean_high":0.1940762887,"std_high":0.0015567577,"min_low":0.1888,"max_low":0.196,"mode_low":0.1923,"sum_low":18.7145,"mean_low":0.1929329897,"std_low":0.0015857912,"min_close":0.1897,"max_close":0.1969,"mode_close":0.1949,"sum_close":18.773,"mean_close":0.1935360825,"std_close":0.0015746154,"min_volume":19444.1,"max_volume":274623.2,"mode_volume":19444.1,"sum_volume":6917246.0,"mean_volume":71311.8144329897,"std_volume":46936.6942597731,"min_close_time":1713658499999,"max_close_time":1713744899999,"mode_close_time":1713658499999,"sum_close_time":166229064899903,"mean_close_time":1713701699999.0,"std_close_time":25330909.9718111195,"min_quote_asset_volume":3744.7019,"max_quote_asset_volume":52802.74897,"mode_quote_asset_volume":3744.7019,"sum_quote_asset_volume":1338014.9057999998,"mean_quote_asset_volume":13793.9681010309,"std_quote_asset_volume":9032.9658112333,"min_number_of_trades":40,"max_number_of_trades":430,"mode_number_of_trades":84,"sum_number_of_trades":13220,"mean_number_of_trades":136.2886597938,"std_number_of_trades":66.7386005814,"min_taker_buy_base_asset_volume":6403.4,"max_taker_buy_base_asset_volume":113513.9,"mode_taker_buy_base_asset_volume":6403.4,"sum_taker_buy_base_asset_volume":3678611.0,"mean_taker_buy_base_asset_volume":37923.824742268,"std_taker_buy_base_asset_volume":22710.8302442727,"min_taker_buy_quote_asset_volume":1239.9591,"max_taker_buy_quote_asset_volume":21884.68638,"mode_taker_buy_quote_asset_volume":1239.9591,"sum_taker_buy_quote_asset_volume":712152.61021,"mean_taker_buy_quote_asset_volume":7341.779486701,"std_taker_buy_quote_asset_volume":4392.1556482664,"min_ignore":0,"max_ignore":0,"mode_ignore":0,"sum_ignore":0,"mean_ignore":0.0,"std_ignore":0.0},{"timestamp":"2024-04-22T00:00:00.000","min_open":0.1923,"max_open":0.1998,"mode_open":0.1975,"sum_open":19.1197,"mean_open":0.1971103093,"std_open":0.0018746936,"min_high":0.1929,"max_high":0.2001,"mode_high":0.198,"sum_high":19.1841,"mean_high":0.1977742268,"std_high":0.0017538219,"min_low":0.1915,"max_low":0.1991,"mode_low":0.1983,"sum_low":19.0646,"mean_low":0.196542268,"std_low":0.0019571895,"min_close":0.1923,"max_close":0.1999,"mode_close":0.1973,"sum_close":19.1294,"mean_close":0.1972103093,"std_close":0.0018370314,"min_volume":15246.5,"max_volume":432406.3,"mode_volume":15246.5,"sum_volume":8517072.2000000011,"mean_volume":87804.8680412371,"std_volume":55030.4628407787,"min_close_time":1713744899999,"max_close_time":1713831299999,"mode_close_time":1713744899999,"sum_close_time":166237445699903,"mean_close_time":1713788099999.0,"std_close_time":25330909.9718111195,"min_quote_asset_volume":3028.35925,"max_quote_asset_volume":85956.13826,"mode_quote_asset_volume":3028.35925,"sum_quote_asset_volume":1677950.5993000001,"mean_quote_asset_volume":17298.4597865979,"std_quote_asset_volume":10859.6572072511,"min_number_of_trades":49,"max_number_of_trades":444,"mode_number_of_trades":106,"sum_number_of_trades":16950,"mean_number_of_trades":174.7422680412,"std_number_of_trades":79.9991247804,"min_taker_buy_base_asset_volume":7947.7,"max_taker_buy_base_asset_volume":249770.9,"mode_taker_buy_base_asset_volume":7947.7,"sum_taker_buy_base_asset_volume":4291223.2000000002,"mean_taker_buy_base_asset_volume":44239.4144329897,"std_taker_buy_base_asset_volume":29278.2088803651,"min_taker_buy_quote_asset_volume":1578.49094,"max_taker_buy_quote_asset_volume":49665.67598,"mode_taker_buy_quote_asset_volume":1578.49094,"sum_taker_buy_quote_asset_volume":845830.0972899999,"mean_taker_buy_quote_asset_volume":8719.8979102062,"std_taker_buy_quote_asset_volume":5788.9102339665,"min_ignore":0,"max_ignore":0,"mode_ignore":0,"sum_ignore":0,"mean_ignore":0.0,"std_ignore":0.0},{"timestamp":"2024-04-23T00:00:00.000","min_open":0.1953,"max_open":0.2022,"mode_open":0.1976,"sum_open":19.3012,"mean_open":0.1989814433,"std_open":0.0016069724,"min_high":0.1962,"max_high":0.2031,"mode_high":0.2004,"sum_high":19.3654,"mean_high":0.199643299,"std_high":0.0015997986,"min_low":0.1946,"max_low":0.2012,"mode_low":0.2001,"sum_low":19.243,"mean_low":0.1983814433,"std_low":0.00155559,"min_close":0.1953,"max_close":0.2022,"mode_close":0.2001,"sum_close":19.3058,"mean_close":0.199028866,"std_close":0.0016232657,"min_volume":17173.7,"max_volume":710445.6,"mode_volume":17173.7,"sum_volume":10045973.0,"mean_volume":103566.7319587629,"std_volume":93008.3851804442,"min_close_time":1713831299999,"max_close_time":1713917699999,"mode_close_time":1713831299999,"sum_close_time":166245826499903,"mean_close_time":1713874499999.0,"std_close_time":25330909.9718111195,"min_quote_asset_volume":3402.67215,"max_quote_asset_volume":142448.90259,"mode_quote_asset_volume":3402.67215,"sum_quote_asset_volume":1999517.6193799998,"mean_quote_asset_volume":20613.5837049485,"std_quote_asset_volume":18544.8527721454,"min_number_of_trades":39,"max_number_of_trades":995,"mode_number_of_trades":82,"sum_number_of_trades":18701,"mean_number_of_trades":192.793814433,"std_number_of_trades":137.8394248561,"min_taker_buy_base_asset_volume":7107.3,"max_taker_buy_base_asset_volume":553012.4,"mode_taker_buy_base_asset_volume":7107.3,"sum_taker_buy_base_asset_volume":5291626.8999999994,"mean_taker_buy_base_asset_volume":54552.8546391753,"std_taker_buy_base_asset_volume":63320.6191655544,"min_taker_buy_quote_asset_volume":1408.16308,"max_taker_buy_quote_asset_volume":110908.68923,"mode_taker_buy_quote_asset_volume":1408.16308,"sum_taker_buy_quote_asset_volume":1054636.85724,"mean_taker_buy_quote_asset_volume":10872.54492,"std_taker_buy_quote_asset_volume":12682.1011696186,"min_ignore":0,"max_ignore":0,"mode_ignore":0,"sum_ignore":0,"mean_ignore":0.0,"std_ignore":0.0},{"timestamp":"2024-04-24T00:00:00.000","min_open":0.1852,"max_open":0.2069,"mode_open":0.2047,"sum_open":19.2225,"mean_open":0.1981701031,"std_open":0.0065940656,"min_high":0.1866,"max_high":0.2091,"mode_high":0.2051,"sum_high":19.2899,"mean_high":0.1988649485,"std_high":0.0065424263,"min_low":0.1845,"max_low":0.2061,"mode_low":0.2034,"sum_low":19.1412,"mean_low":0.1973319588,"std_low":0.006709439,"min_close":0.1851,"max_close":0.207,"mode_close":0.19,"sum_close":19.2115,"mean_close":0.198056701,"std_close":0.0066607511,"min_volume":11698.5,"max_volume":968668.9,"mode_volume":11698.5,"sum_volume":14008747.7000000011,"mean_volume":144420.0793814433,"std_volume":168246.8682653323,"min_close_time":1713917699999,"max_close_time":1714004099999,"mode_close_time":1713917699999,"sum_close_time":166254207299903,"mean_close_time":1713960899999.0,"std_close_time":25330909.9718111195,"min_quote_asset_volume":2369.98487,"max_quote_asset_volume":197252.90761,"mode_quote_asset_volume":2369.98487,"sum_quote_asset_volume":2775176.08519,"mean_quote_asset_volume":28610.0627339175,"std_quote_asset_volume":33519.8639131189,"min_number_of_trades":47,"max_number_of_trades":1474,"mode_number_of_trades":99,"sum_number_of_trades":24275,"mean_number_of_trades":250.2577319588,"std_number_of_trades":235.3082321813,"min_taker_buy_base_asset_volume":6884.8,"max_taker_buy_base_asset_volume":359949.5,"mode_taker_buy_base_asset_volume":6884.8,"sum_taker_buy_base_asset_volume":6511551.7999999998,"mean_taker_buy_base_asset_volume":67129.4,"std_taker_buy_base_asset_volume":73036.612663567,"min_taker_buy_quote_asset_volume":1393.66918,"max_taker_buy_quote_asset_volume":74544.35572,"mode_taker_buy_quote_asset_volume":1393.66918,"sum_taker_buy_quote_asset_volume":1290751.2937599998,"mean_taker_buy_quote_asset_volume":13306.7143686598,"std_taker_buy_quote_asset_volume":14600.9540295788,"min_ignore":0,"max_ignore":0,"mode_ignore":0,"sum_ignore":0,"mean_ignore":0.0,"std_ignore":0.0},{"timestamp":"2024-04-25T00:00:00.000","min_open":0.181,"max_open":0.19,"mode_open":0.1838,"sum_open":18.0397,"mean_open":0.1859762887,"std_open":0.0024843583,"min_high":0.1815,"max_high":0.1908,"mode_high":0.1856,"sum_high":18.104,"mean_high":0.1866391753,"std_high":0.0023792312,"min_low":0.18,"max_low":0.1897,"mode_low":0.1841,"sum_low":17.9767,"mean_low":0.1853268041,"std_low":0.0026341316,"min_close":0.1808,"max_close":0.1902,"mode_close":0.1888,"sum_close":18.0434,"mean_close":0.186014433,"std_close":0.0025277621,"min_volume":13497.2,"max_volume":337871.1,"mode_volume":13497.2,"sum_volume":9784284.3000000007,"mean_volume":100868.9103092784,"std_volume":62106.1976179385,"min_close_time":1714004099999,"max_close_time":1714090499999,"mode_close_time":1714004099999,"sum_close_time":166262588099903,"mean_close_time":1714047299999.0,"std_close_time":25330909.9718111195,"min_quote_asset_volume":2541.97137,"max_quote_asset_volume":61145.02839,"mode_quote_asset_volume":2541.97137,"sum_quote_asset_volume":1812537.7352,"mean_quote_asset_volume":18685.9560329897,"std_quote_asset_volume":11358.2120264309,"min_number_of_trades":34,"max_number_of_trades":607,"mode_number_of_trades":163,"sum_number_of_trades":18058,"mean_number_of_trades":186.1649484536,"std_number_of_trades":101.8743793859,"min_taker_buy_base_asset_volume":293.0,"max_taker_buy_base_asset_volume":179008.8,"mode_taker_buy_base_asset_volume":293.0,"sum_taker_buy_base_asset_volume":5107540.6999999993,"mean_taker_buy_base_asset_volume":52655.0587628866,"std_taker_buy_base_asset_volume":35367.6023979714,"min_taker_buy_quote_asset_volume":55.42491,"max_taker_buy_quote_asset_volume":32421.1832,"mode_taker_buy_quote_asset_volume":55.42491,"sum_taker_buy_quote_asset_volume":946303.3282900001,"mean_taker_buy_quote_asset_volume":9755.7044153608,"std_taker_buy_quote_asset_volume":6484.8983798522,"min_ignore":0,"max_ignore":0,"mode_ignore":0,"sum_ignore":0,"mean_ignore":0.0,"std_ignore":0.0},{"timestamp":"2024-04-26T00:00:00.000","min_open":0.1828,"max_open":0.1891,"mode_open":0.1852,"sum_open":17.2692,"mean_open":0.1856903226,"std_open":0.0011355007,"min_high":0.1835,"max_high":0.1899,"mode_high":0.1857,"sum_high":17.3365,"mean_high":0.1864139785,"std_high":0.0012567722,"min_low":0.1823,"max_low":0.1881,"mode_low":0.1848,"sum_low":17.2054,"mean_low":0.1850043011,"std_low":0.0010965275,"min_close":0.1828,"max_close":0.1891,"mode_close":0.1847,"sum_close":17.2664,"mean_close":0.1856602151,"std_close":0.0011227044,"min_volume":11901.4,"max_volume":657276.0,"mode_volume":11901.4,"sum_volume":10059739.9000000022,"mean_volume":108169.2462365592,"std_volume":84525.0273242019,"min_close_time":1714090499999,"max_close_time":1714173299999,"mode_close_time":1714090499999,"sum_close_time":159414266699907,"mean_close_time":1714131899999.0,"std_close_time":24291665.2372784019,"min_quote_asset_volume":2205.0984,"max_quote_asset_volume":123287.5505,"mode_quote_asset_volume":2205.0984,"sum_quote_asset_volume":1870426.14542,"mean_quote_asset_volume":20112.1090905376,"std_quote_asset_volume":15798.5371160783,"min_number_of_trades":37,"max_number_of_trades":839,"mode_number_of_trades":160,"sum_number_of_trades":20395,"mean_number_of_trades":219.3010752688,"std_number_of_trades":122.4480178037,"min_taker_buy_base_asset_volume":7569.5,"max_taker_buy_base_asset_volume":511710.7,"mode_taker_buy_base_asset_volume":7569.5,"sum_taker_buy_base_asset_volume":5762852.6999999993,"mean_taker_buy_base_asset_volume":61966.1580645161,"std_taker_buy_base_asset_volume":64482.5581303771,"min_taker_buy_quote_asset_volume":1410.50822,"max_taker_buy_quote_asset_volume":96022.12629,"mode_taker_buy_quote_asset_volume":1410.50822,"sum_taker_buy_quote_asset_volume":1072047.1487500002,"mean_taker_buy_quote_asset_volume":11527.3886962366,"std_taker_buy_quote_asset_volume":12069.6546124847,"min_ignore":0,"max_ignore":0,"mode_ignore":0,"sum_ignore":0,"mean_ignore":0.0,"std_ignore":0.0}]