[{"timestamp":"2024-04-15T00:00:00.000","min_open":1.007,"max_open":1.126,"mode_open":1.09,"sum_open":104.025,"mean_open":1.0724226804,"std_open":0.037667082,"min_high":1.011,"max_high":1.129,"mode_high":1.027,"sum_high":104.503,"mean_high":1.0773505155,"std_high":0.0376519259,"min_low":0.99,"max_low":1.119,"mode_low":1.113,"sum_low":103.457,"mean_low":1.0665670103,"std_low":0.0384322746,"min_close":1.006,"max_close":1.128,"mode_close":1.087,"sum_close":103.932,"mean_close":1.0714639175,"std_close":0.0378888346,"min_volume":493.39,"max_volume":55098.36,"mode_volume":493.39,"sum_volume":1412309.48,"mean_volume":14559.8915463918,"std_volume":10874.0873506354,"min_close_time":1713140099999,"max_close_time":1713226499999,"mode_close_time":1713140099999,"sum_close_time":166178780099903,"mean_close_time":1713183299999.0,"std_close_time":25330909.9718111195,"min_quote_asset_volume":552.56675,"max_quote_asset_volume":60007.00852,"mode_quote_asset_volume":552.56675,"sum_quote_asset_volume":1512337.3601800001,"mean_quote_asset_volume":15591.1068059794,"std_quote_asset_volume":11647.3866963505,"min_number_of_trades":26,"max_number_of_trades":1197,"mode_number_of_trades":117,"sum_number_of_trades":32378,"mean_number_of_trades":333.793814433,"std_number_of_trades":254.4837068354,"min_taker_buy_base_asset_volume":213.17,"max_taker_buy_base_asset_volume":24064.16,"mode_taker_buy_base_asset_volume":213.17,"sum_taker_buy_base_asset_volume":665478.1699999999,"mean_taker_buy_base_asset_volume":6860.5996907216,"std_taker_buy_base_asset_volume":5546.1263967469,"min_taker_buy_quote_asset_volume":238.89926,"max_taker_buy_quote_asset_volume":26717.70179,"mode_taker_buy_quote_asset_volume":238.89926,"sum_taker_buy_quote_asset_volume":712536.30966,"mean_taker_buy_quote_asset_volume":7345.735151134,"std_taker_buy_quote_asset_volume":5949.1536381999,"min_ignore":0,"max_ignore":0,"mode_ignore":0,"sum_ignore":0,"mean_ignore":0.0,"std_ignore":0.0},{"timestamp":"2024-04-16T00:00:00.000","min_open":0.986,"max_open":1.042,"mode_open":1.032,"sum_open":98.744,"mean_open":1.0179793814,"std_open":0.0145344271,"min_high":0.992,"max_high":1.047,"mode_high":1.03,"sum_high":99.311,"mean_high":1.0238247423,"std_high":0.0136717549,"min_low":0.981,"max_low":1.039,"mode_low":1.034,"sum_low":98.236,"mean_low":1.012742268,"std_low":0.0152829414,"min_close":0.985,"max_close":1.042,"mode_close":1.023,"sum_close":98.761,"mean_close":1.0181546392,"std_close":0.0145697605,"min_volume":592.79,"max_volume":70952.23,"mode_volume":592.79,"sum_volume":1439841.3200000001,"mean_volume":14843.7249484536,"std_volume":13218.4522408509,"min_close_time":1713226499999,"max_close_time":1713312899999,"mode_close_time":1713226499999,"sum_close_time":166187160899903,"mean_close_time":1713269699999.0,"std_close_time":25330909.9718111195,"min_quote_asset_volume":609.98806,"max_quote_asset_volume":71389.33092,"mode_quote_asset_volume":609.98806,"sum_quote_asset_volume":1461176.3235899999,"mean_quote_asset_volume":15063.6734390722,"std_quote_asset_volume":13320.3910380827,"min_number_of_trades":28,"max_number_of_trades":1104,"mode_number_of_trades":50,"sum_number_of_trades":34104,"mean_number_of_trades":351.587628866,"std_number_of_trades":256.797251112,"min_taker_buy_base_asset_volume":341.49,"max_taker_buy_base_asset_volume":33014.53,"mode_taker_buy_base_asset_volume":341.49,"sum_taker_buy_base_asset_volume":665291.4,"mean_taker_buy_base_asset_volume":6858.6742268041,"std_taker_buy_base_asset_volume":6271.7267517578,"min_taker_buy_quote_asset_volume":350.32472,"max_taker_buy_quote_asset_volume":33688.06385,"mode_taker_buy_quote_asset_volume":350.32472,"sum_taker_buy_quote_asset_volume":675552.51409,"mean_taker_buy_quote_asset_volume":6964.4589081443,"std_taker_buy_quote_asset_volume":6348.1790536663,"min_ignore":0,"max_ignore":0,"mode_ignore":0,"sum_ignore":0,"mean_ignore":0.0,"std_ignore":0.0},{"timestamp":"2024-04-17T00:00:00.000","min_open":0.975,"max_open":1.063,"mode_open":1.023,"sum_open":99.246,"mean_open":1.0231546392,"std_open":0.019062037,"min_high":0.982,"max_high":1.09,"mode_high":1.024,"sum_high":99.92,"mean_high":1.0301030928,"std_high":0.0201657117,"min_low":0.972,"max_low":1.057,"mode_low":1.019,"sum_low":98.746,"mean_low":1.018,"std_low":0.0184628004,"min_close":0.974,"max_close":1.063,"mode_close":1.017,"sum_close":99.273,"mean_close":1.0234329897,"std_close":0.0192011866,"min_volume":419.38,"max_volume":250349.03,"mode_volume":419.38,"sum_volume":3070861.0699999998,"mean_volume":31658.3615463918,"std_volume":42586.3861420213,"min_close_time":1713312899999,"max_close_time":1713399299999,"mode_close_time":1713312899999,"sum_close_time":166195541699903,"mean_close_time":1713356099999.0,"std_close_time":25330909.9718111195,"min_quote_asset_volume":429.68828,"max_quote_asset_volume":255654.96808,"mode_quote_asset_volume":429.68828,"sum_quote_asset_volume":3142849.8783900002,"mean_quote_asset_volume":32400.5142102062,"std_quote_asset_volume":43823.580593696,"min_number_of_trades":22,"max_number_of_trades":2912,"mode_number_of_trades":37,"sum_number_of_trades":46643,"mean_number_of_trades":480.8556701031,"std_number_of_trades":489.3213623158,"min_taker_buy_base_asset_volume":148.28,"max_taker_buy_base_asset_volume":140980.82,"mode_taker_buy_base_asset_volume":148.28,"sum_taker_buy_base_asset_volume":1519364.98,"mean_taker_buy_base_asset_volume":15663.5564948454,"std_taker_buy_base_asset_volume":23541.3720880982,"min_taker_buy_quote_asset_volume":152.05176,"max_taker_buy_quote_asset_volume":150969.31233,"mode_taker_buy_quote_asset_volume":152.05176,"sum_taker_buy_quote_asset_volume":1559894.6310599998,"mean_taker_buy_quote_asset_volume":16081.3879490722,"std_taker_buy_quote_asset_volume":24395.6398856295,"min_ignore":0,"max_ignore":0,"mode_ignore":0,"sum_ignore":0,"mean_ignore":0.0,"std_ignore":0.0},{"timestamp":"2024-04-18T00:00:00.000","min_open":1.03,"max_open":1.085,"mode_open":1.04,"sum_open":101.659,"mean_open":1.0480309278,"std_open":0.0097856758,"min_high":1.034,"max_high":1.096,"mode_high":1.05,"sum_high":102.164,"mean_high":1.0532371134,"std_high":0.0104251031,"min_low":1.018,"max_low":1.079,"mode_low":1.053,"sum_low":101.137,"mean_low":1.0426494845,"std_low":0.009845728,"min_close":1.03,"max_close":1.085,"mode_close":1.046,"sum_close":101.66,"mean_close":1.0480412371,"std_close":0.0098403056,"min_volume":1123.9,"max_volume":217834.92,"mode_volume":1123.9,"sum_volume":1826894.1299999999,"mean_volume":18833.9601030928,"std_volume":28217.2805731608,"min_close_time":1713399299999,"max_close_time":1713485699999,"mode_close_time":1713399299999,"sum_close_time":166203922499903,"mean_close_time":1713442499999.0,"std_close_time":25330909.9718111195,"min_quote_asset_volume":1188.98831,"max_quote_asset_volume":228217.60777,"mode_quote_asset_volume":1188.98831,"sum_quote_asset_volume":1917105.7978700001,"mean_quote_asset_volume":19763.9772976289,"std_quote_asset_volume":29545.3436515027,"min_number_of_trades":31,"max_number_of_trades":2804,"mode_number_of_trades":76,"sum_number_of_trades":35040,"mean_number_of_trades":361.2371134021,"std_number_of_trades":405.4087385281,"min_taker_buy_base_asset_volume":301.58,"max_taker_buy_base_asset_volume":80162.51,"mode_taker_buy_base_asset_volume":301.58,"sum_taker_buy_base_asset_volume":900379.36,"mean_taker_buy_base_asset_volume":9282.261443299,"std_taker_buy_base_asset_volume":12586.510102097,"min_taker_buy_quote_asset_volume":315.12779,"max_taker_buy_quote_asset_volume":83062.19839,"mode_taker_buy_quote_asset_volume":315.12779,"sum_taker_buy_quote_asset_volume":946584.3122800001,"mean_taker_buy_quote_asset_volume":9758.6011575258,"std_taker_buy_quote_asset_volume":13243.96878628,"min_ignore":0,"max_ignore":0,"mode_ignore":0,"sum_ignore":0,"mean_ignore":0.0,"std_ignore":0.0},{"timestamp":"2024-04-19T00:00:00.000","min_open":0.995,"max_open":1.087,"mode_open":1.08,"sum_open":102.823,"mean_open":1.0600309278,"std_open":0.0247611312,"min_high":1.004,"max_high":1.1,"mode_high":1.083,"sum_high":103.411,"mean_high":1.0660927835,"std_high":0.0247937671,"min_low":0.991,"max_low":1.08,"mode_low":1.072,"sum_low":102.298,"mean_low":1.0546185567,"std_low":0.0250318311,"min_close":0.995,"max_close":1.088,"mode_close":1.08,"sum_close":102.841,"mean_close":1.0602164948,"std_close":0.0244962696,"min_volume":1315.73,"max_volume":100000.89,"mode_volume":1315.73,"sum_volume":2064643.2000000002,"mean_volume":21284.981443299,"std_volume":18385.7442411491,"min_close_time":1713485699999,"max_close_time":1713572099999,"mode_close_time":1713485699999,"sum_close_time":166212303299903,"mean_close_time":1713528899999.0,"std_close_time":25330909.9718111195,"min_quote_asset_volume":1414.14637,"max_quote_asset_volume":103224.21358,"mode_quote_asset_volume":1414.14637,"sum_quote_asset_volume":2179720.92294,"mean_quote_asset_volume":22471.3497210309,"std_quote_asset_volume":19242.5438707031,"min_number_of_trades":43,"max_number_of_trades":1564,"mode_number_of_trades":60,"sum_number_of_trades":36883,"mean_number_of_trades":380.2371134021,"std_number_of_trades":293.7826142602,"min_taker_buy_base_asset_volume":473.95,"max_taker_buy_base_asset_volume":48054.78,"mode_taker_buy_base_asset_volume":473.95,"sum_taker_buy_base_asset_volume":1002828.4299999999,"mean_taker_buy_base_asset_volume":10338.4374226804,"std_taker_buy_base_asset_volume":9177.5608213609,"min_taker_buy_quote_asset_volume":513.09565,"max_taker_buy_quote_asset_volume":50088.69767,"mode_taker_buy_quote_asset_volume":513.09565,"sum_taker_buy_quote_asset_volume":1061979.4748800001,"mean_taker_buy_quote_asset_volume":10948.2420090722,"std_taker_buy_quote_asset_volume":9725.3521961439,"min_ignore":0,"max_ignore":0,"mode_ignore":0,"sum_ignore":0,"mean_ignore":0.0,"std_ignore":0.0},{"timestamp":"2024-04-20T00:00:00.000","min_open":1.06,"max_open":1.202,"mode_open":1.077,"sum_open":108.982,"mean_open":1.1235257732,"std_open":0.0506028435,"min_high":1.066,"max_high":1.205,"mode_high":1.197,"sum_high":109.829,"mean_high":1.132257732,"std_high":0.0515819086,"min_low":1.053,"max_low":1.191,"mode_low":1.074,"sum_low":108.461,"mean_low":1.1181546392,"std_low":0.0493742806,"min_close":1.062,"max_close":1.2,"mode_close":1.075,"sum_close":109.102,"mean_close":1.1247628866,"std_close":0.0507314772,"min_volume":1195.15,"max_volume":289485.53,"mode_volume":1195.15,"sum_volume":3091791.7599999998,"mean_volume":31874.1418556701,"std_volume":48369.9698622785,"min_close_time":1713572099999,"max_close_time":1713658499999,"mode_close_time":1713572099999,"sum_close_time":166220684099903,"mean_close_time":1713615299999.0,"std_close_time":25330909.9718111195,"min_quote_asset_volume":1280.49448,"max_quote_asset_volume":313986.67311,"mode_quote_asset_volume":1280.49448,"sum_quote_asset_volume":3468937.63619,"mean_quote_asset_volume":35762.2436720619,"std_quote_asset_volume":53826.2764679138,"min_number_of_trades":23,"max_number_of_trades":3455,"mode_number_of_trades":72,"sum_number_of_trades":58337,"mean_number_of_trades":601.412371134,"std_number_of_trades":638.6554847323,"min_taker_buy_base_asset_volume":235.47,"max_taker_buy_base_asset_volume":179928.42,"mode_taker_buy_base_asset_volume":235.47,"sum_taker_buy_base_asset_volume":1653371.7199999997,"mean_taker_buy_base_asset_volume":17045.0692783505,"std_taker_buy_base_asset_volume":28703.3668460267,"min_taker_buy_quote_asset_volume":252.57614,"max_taker_buy_quote_asset_volume":206536.38508,"mode_taker_buy_quote_asset_volume":252.57614,"sum_taker_buy_quote_asset_volume":1855796.6376199999,"mean_taker_buy_quote_asset_volume":19131.9240991753,"std_taker_buy_quote_asset_volume":32099.2090831016,"min_ignore":0,"max_ignore":0,"mode_ignore":0,"sum_ignore":0,"mean_ignore":0.0,"std_ignore":0.0},{"timestamp":"2024-04-21T00:00:00.000","min_open":1.184,"max_open":1.234,"mode_open":1.213,"sum_open":117.478,"mean_open":1.2111134021,"std_open":0.0104591231,"min_high":1.191,"max_high":1.248,"mode_high":1.222,"sum_high":118.234,"mean_high":1.2189072165,"std_high":0.0114882934,"min_low":1.175,"max_low":1.225,"mode_low":1.211,"sum_low":116.893,"mean_low":1.2050824742,"std_low":0.0105442225,"min_close":1.184,"max_close":1.235,"mode_close":1.221,"sum_close":117.503,"mean_close":1.211371134,"std_close":0.0102989882,"min_volume":635.42,"max_volume":89247.43,"mode_volume":635.42,"sum_volume":1912464.8899999999,"mean_volume":19716.1328865979,"std_volume":17352.6701818473,"min_close_time":1713658499999,"max_close_time":1713744899999,"mode_close_time":1713658499999,"sum_close_time":166229064899903,"mean_close_time":1713701699999.0,"std_close_time":25330909.9718111195,"min_quote_asset_volume":776.30156,"max_quote_asset_volume":108882.09502,"mode_quote_asset_volume":776.30156,"sum_quote_asset_volume":2316849.2575400001,"mean_quote_asset_volume":23885.043892165,"std_quote_asset_volume":21043.224240535,"min_number_of_trades":27,"max_number_of_trades":1988,"mode_number_of_trades":79,"sum_number_of_trades":58698,"mean_number_of_trades":605.1340206186,"std_number_of_trades":540.4540650552,"min_taker_buy_base_asset_volume":316.51,"max_taker_buy_base_asset_volume":50426.18,"mode_taker_buy_base_asset_volume":316.51,"sum_taker_buy_base_asset_volume":946862.67,"mean_taker_buy_base_asset_volume":9761.4708247423,"std_taker_buy_base_asset_volume":9539.8203008774,"min_taker_buy_quote_asset_volume":386.4289,"max_taker_buy_quote_asset_volume":61640.64924,"mode_taker_buy_quote_asset_volume":386.4289,"sum_taker_buy_quote_asset_volume":1148252.8591400001,"mean_taker_buy_quote_asset_volume":11837.6583416495,"std_taker_buy_quote_asset_volume":11592.123254267,"min_ignore":0,"max_ignore":0,"mode_ignore":0,"sum_ignore":0,"mean_ignore":0.0,"std_ignore":0.0},{"timestamp":"2024-04-22T00:00:00.000","min_open":1.209,"max_open":1.27,"mode_open":1.249,"sum_open":120.53,"mean_open":1.2425773196,"std_open":0.0147527081,"min_high":1.215,"max_high":1.289,"mode_high":1.255,"sum_high":121.173,"mean_high":1.2492061856,"std_high":0.0150872036,"min_low":1.205,"max_low":1.261,"mode_low":1.249,"sum_low":120.0,"mean_low":1.2371134021,"std_low":0.0138923512,"min_close":1.21,"max_close":1.27,"mode_close":1.249,"sum_close":120.573,"mean_close":1.2430206186,"std_close":0.0144791368,"min_volume":1021.17,"max_volume":110335.33,"mode_volume":1021.17,"sum_volume":1748474.3200000001,"mean_volume":18025.5084536082,"std_volume":19099.3682963129,"min_close_time":1713744899999,"max_close_time":1713831299999,"mode_close_time":1713744899999,"sum_close_time":166237445699903,"mean_close_time":1713788099999.0,"std_close_time":25330909.9718111195,"min_quote_asset_volume":1275.60469,"max_quote_asset_volume":139520.51687,"mode_quote_asset_volume":1275.60469,"sum_quote_asset_volume":2177759.1438199999,"mean_quote_asset_volume":22451.1251940206,"std_quote_asset_volume":23925.7714850408,"min_number_of_trades":35,"max_number_of_trades":2122,"mode_number_of_trades":88,"sum_number_of_trades":46773,"mean_number_of_trades":482.1958762887,"std_number_of_trades":458.8133162295,"min_taker_buy_base_asset_volume":529.68,"max_taker_buy_base_asset_volume":77370.77,"mode_taker_buy_base_asset_volume":529.68,"sum_taker_buy_base_asset_volume":910517.23,"mean_taker_buy_base_asset_volume":9386.7755670103,"std_taker_buy_base_asset_volume":12076.5866005897,"min_taker_buy_quote_asset_volume":669.70147,"max_taker_buy_quote_asset_volume":97878.40941,"mode_taker_buy_quote_asset_volume":669.70147,"sum_taker_buy_quote_asset_volume":1135566.3138899999,"mean_taker_buy_quote_asset_volume":11706.8692153608,"std_taker_buy_quote_asset_volume":15165.0463496002,"min_ignore":0,"max_ignore":0,"mode_ignore":0,"sum_ignore":0,"mean_ignore":0.0,"std_ignore":0.0},{"timestamp":"2024-04-23T00:00:00.000","min_open":1.235,"max_open":1.264,"mode_open":1.259,"sum_open":121.333,"mean_open":1.2508556701,"std_open":0.0082978281,"min_high":1.238,"max_high":1.269,"mode_high":1.26,"sum_high":121.776,"mean_high":1.2554226804,"std_high":0.0085924325,"min_low":1.233,"max_low":1.261,"mode_low":1.239,"sum_low":120.959,"mean_low":1.247,"std_low":0.0079726094,"min_close":1.235,"max_close":1.265,"mode_close":1.259,"sum_close":121.358,"mean_close":1.2511134021,"std_close":0.0084875844,"min_volume":630.58,"max_volume":44913.51,"mode_volume":630.58,"sum_volume":1186682.3600000001,"mean_volume":12233.8387628866,"std_volume":10940.3769165796,"min_close_time":1713831299999,"max_close_time":1713917699999,"mode_close_time":1713831299999,"sum_close_time":166245826499903,"mean_close_time":1713874499999.0,"std_close_time":25330909.9718111195,"min_quote_asset_volume":793.49466,"max_quote_asset_volume":56428.19363,"mode_quote_asset_volume":793.49466,"sum_quote_asset_volume":1485611.6774200001,"mean_quote_asset_volume":15315.584303299,"std_quote_asset_volume":13723.2532378565,"min_number_of_trades":26,"max_number_of_trades":1501,"mode_number_of_trades":39,"sum_number_of_trades":32645,"mean_number_of_trades":336.5463917526,"std_number_of_trades":313.1864467527,"min_taker_buy_base_asset_volume":235.48,"max_taker_buy_base_asset_volume":36456.34,"mode_taker_buy_base_asset_volume":235.48,"sum_taker_buy_base_asset_volume":613681.05,"mean_taker_buy_base_asset_volume":6326.6087628866,"std_taker_buy_base_asset_volume":6420.0290378429,"min_taker_buy_quote_asset_volume":296.52356,"max_taker_buy_quote_asset_volume":45803.64867,"mode_taker_buy_quote_asset_volume":296.52356,"sum_taker_buy_quote_asset_volume":769121.3341300001,"mean_taker_buy_quote_asset_volume":7929.085918866,"std_taker_buy_quote_asset_volume":8067.9837564262,"min_ignore":0,"max_ignore":0,"mode_ignore":0,"sum_ignore":0,"mean_ignore":0.0,"std_ignore":0.0},{"timestamp":"2024-04-24T00:00:00.000","min_open":1.172,"max_open":1.301,"mode_open":1.199,"sum_open":121.251,"mean_open":1.2500103093,"std_open":0.0418067217,"min_high":1.183,"max_high":1.303,"mode_high":1.294,"sum_high":121.74,"mean_high":1.2550515464,"std_high":0.0416113894,"min_low":1.167,"max_low":1.297,"mode_low":1.268,"sum_low":120.685,"mean_low":1.2441752577,"std_low":0.0429224131,"min_close":1.171,"max_close":1.301,"mode_close":1.27,"sum_close":121.17,"mean_close":1.2491752577,"std_close":0.0422233669,"min_volume":816.19,"max_volume":182416.59,"mode_volume":816.19,"sum_volume":2098035.2999999998,"mean_volume":21629.2298969072,"std_volume":23660.8970550065,"min_close_time":1713917699999,"max_close_time":1714004099999,"mode_close_time":1713917699999,"sum_close_time":166254207299903,"mean_close_time":1713960899999.0,"std_close_time":25330909.9718111195,"min_quote_asset_volume":1038.88798,"max_quote_asset_volume":219388.27738,"mode_quote_asset_volume":1038.88798,"sum_quote_asset_volume":2591930.7830699999,"mean_quote_asset_volume":26720.9359079381,"std_quote_asset_volume":28634.4692588268,"min_number_of_trades":23,"max_number_of_trades":2274,"mode_number_of_trades":77,"sum_number_of_trades":46707,"mean_number_of_trades":481.5154639175,"std_number_of_trades":444.0918193676,"min_taker_buy_base_asset_volume":167.67,"max_taker_buy_base_asset_volume":43059.48,"mode_taker_buy_base_asset_volume":167.67,"sum_taker_buy_base_asset_volume":981639.0099999999,"mean_taker_buy_base_asset_volume":10119.9897938144,"std_taker_buy_base_asset_volume":9709.8171236931,"min_taker_buy_quote_asset_volume":213.78308,"max_taker_buy_quote_asset_volume":52102.47904,"mode_taker_buy_quote_asset_volume":213.78308,"sum_taker_buy_quote_asset_volume":1212004.20545,"mean_taker_buy_quote_asset_volume":12494.8887159794,"std_taker_buy_quote_asset_volume":11774.6457732045,"min_ignore":0,"max_ignore":0,"mode_ignore":0,"sum_ignore":0,"mean_ignore":0.0,"std_ignore":0.0},{"timestamp":"2024-04-25T00:00:00.000","min_open":1.135,"max_open":1.208,"mode_open":1.161,"sum_open":113.904,"mean_open":1.1742680412,"std_open":0.0188643819,"min_high":1.146,"max_high":1.242,"mode_high":1.164,"sum_high":114.559,"mean_high":1.1810206186,"std_high":0.0204450378,"min_low":1.13,"max_low":1.205,"mode_low":1.151,"sum_low":113.447,"mean_low":1.169556701,"std_low":0.0191784216,"min_close":1.135,"max_close":1.209,"mode_close":1.157,"sum_close":113.919,"mean_close":1.1744226804,"std_close":0.0189274025,"min_volume":1197.97,"max_volume":101236.39,"mode_volume":1197.97,"sum_volume":1943883.5900000001,"mean_volume":20040.0370103093,"std_volume":17407.2794815937,"min_close_time":1714004099999,"max_close_time":1714090499999,"mode_close_time":1714004099999,"sum_close_time":166262588099903,"mean_close_time":1714047299999.0,"std_close_time":25330909.9718111195,"min_quote_asset_volume":1442.31044,"max_quote_asset_volume":121615.67587,"mode_quote_asset_volume":1442.31044,"sum_quote_asset_volume":2282404.2479699994,"mean_quote_asset_volume":23529.9407007216,"std_quote_asset_volume":20591.5859311452,"min_number_of_trades":49,"max_number_of_trades":1705,"mode_number_of_trades":239,"sum_number_of_trades":48086,"mean_number_of_trades":495.7319587629,"std_number_of_trades":400.539571377,"min_taker_buy_base_asset_volume":106.72,"max_taker_buy_base_asset_volume":60683.48,"mode_taker_buy_base_asset_volume":106.72,"sum_taker_buy_base_asset_volume":922505.42,"mean_taker_buy_base_asset_volume":9510.3651546392,"std_taker_buy_base_asset_volume":10041.128104272,"min_taker_buy_quote_asset_volume":128.49203,"max_taker_buy_quote_asset_volume":72974.03886,"mode_taker_buy_quote_asset_volume":128.49203,"sum_taker_buy_quote_asset_volume":1085559.2992099999,"mean_taker_buy_quote_asset_volume":11191.3329815464,"std_taker_buy_quote_asset_volume":11949.4529181075,"min_ignore":0,"max_ignore":0,"mode_ignore":0,"sum_ignore":0,"mean_ignore":0.0,"std_ignore":0.0},{"timestamp":"2024-04-26T00:00:00.000","min_open":1.132,"max_open":1.196,"mode_open":1.152,"sum_open":110.768,"mean_open":1.1659789474,"std_open":0.0167585983,"min_high":1.138,"max_high":1.203,"mode_high":1.155,"sum_high":111.189,"mean_high":1.1704105263,"std_high":0.0164675663,"min_low":1.126,"max_low":1.193,"mode_low":1.146,"sum_low":110.345,"mean_low":1.1615263158,"std_low":0.0166470508,"min_close":1.132,"max_close":1.196,"mode_close":1.151,"sum_close":110.724,"mean_close":1.1655157895,"std_close":0.016565064,"min_volume":478.89,"max_volume":53007.8,"mode_volume":478.89,"sum_volume":1306395.0200000003,"mean_volume":13751.5265263158,"std_volume":11219.7548509239,"min_close_time":1714090499999,"max_close_time":1714175099999,"mode_close_time":1714090499999,"sum_close_time":162842615999905,"mean_close_time":1714132799999.0,"std_close_time":24811287.7537623979,"min_quote_asset_volume":556.87869,"max_quote_asset_volume":61481.83669,"mode_quote_asset_volume":556.87869,"sum_quote_asset_volume":1521131.03305,"mean_quote_asset_volume":16011.9056110526,"std_quote_asset_volume":13007.3873052258,"min_number_of_trades":18,"max_number_of_trades":1062,"mode_number_of_trades":58,"sum_number_of_trades":31802,"mean_number_of_trades":334.7578947368,"std_number_of_trades":265.5807252278,"min_taker_buy_base_asset_volume":57.02,"max_taker_buy_base_asset_volume":30571.97,"mode_taker_buy_base_asset_volume":57.02,"sum_taker_buy_base_asset_volume":638125.2500000001,"mean_taker_buy_base_asset_volume":6717.1078947368,"std_taker_buy_base_asset_volume":6011.1301138404,"min_taker_buy_quote_asset_volume":66.25075,"max_taker_buy_quote_asset_volume":35379.33543,"mode_taker_buy_quote_asset_volume":66.25075,"sum_taker_buy_quote_asset_volume":742507.0387899999,"mean_taker_buy_quote_asset_volume":7815.8635662105,"std_taker_buy_quote_asset_volume":6963.1382010188,"min_ignore":0,"max_ignore":0,"mode_ignore":0,"sum_ignore":0,"mean_ignore":0.0,"std_ignore":0.0}]